Workbook

Sheet Data
A1: INVENTORY MANAGEMENT — Assignment 2025-2026
A2: A.U.Th. · Dept. of Mechanical Engineering · Instructor: G. Tagaras | Data & Parameters
A4: Table of contents
A5: Data | B5: Inputs & parameters for both parts
A6: A1_Forecast | B6: Exponential smoothing – choice of α, forecast for months 25-36
A7: A2_A3_EOQ | B7: Reorder point, EOQ, costs, quantity discounts
A8: B1_B2_Systems | B8: Two (s,Q) systems – service measures & costs
A9: B3_Improved | B9: Improved (s,Q) with shortage cost – comparison of 3 systems
A10: B4_Periodic | B10: Periodic-review (R,S) systems – final recommendation
A12: Color legend: | B12: Input (blue) | C12: Formula | D12: Result
A14: PART A — Data
A15: Demand of the last 24 months (units)
A16: Month | B16: 1 | C16: 2 | D16: 3 | E16: 4 | F16: 5 | G16: 6 | H16: 7 | I16: 8 | J16: 9 | K16: 10 | L16: 11 | M16: 12
A17: Demand | B17: 258 | C17: 240 | D17: 194 | E17: 176 | F17: 249 | G17: 172 | H17: 219 | I17: 156 | J17: 175 | K17: 174 | L17: 194 | M17: 276
A18: Month | B18: 13 | C18: 14 | D18: 15 | E18: 16 | F18: 17 | G18: 18 | H18: 19 | I18: 20 | J18: 21 | K18: 22 | L18: 23 | M18: 24
A19: Demand | B19: 138 | C19: 183 | D19: 230 | E19: 196 | F19: 174 | G19: 234 | H19: 244 | I19: 245 | J19: 176 | K19: 140 | L19: 215 | M19: 149
A21: Parameter | B21: Symbol | C21: Value | D21: Description
A22: Purchase cost / unit | B22: v | C22: 100 | D22: €/unit
A23: Fixed ordering cost | B23: A | C23: 750 | D23: €/batch
A24: Lead time | B24: L | C24: 1 | D24: months
A25: Discount factor | B25: E | C25: 1 | D25: % (see A3)
A26: Holding cost rate | B26: r | C26: 0.1 | D26: 10% of unit value / year
A27: Note: the annual holding cost equals r·v = 10% of unit value per year.
A29: PART B — Data (transformers)
A30: Parameter | B30: Symbol | C30: Value | D30: Description
A31: Mean weekly demand | B31: μ | C31: 140 | D31: units/week
A32: Std. dev. of weekly demand | B32: σ | C32: 40 | D32: units/week
A33: Transformer price | B33: v | C33: 80 | D33: €/unit
A34: Holding cost rate | B34: r | C34: 0.1 | D34: per year
A35: Ordering cost | B35: A | C35: 100 | D35: €/order
A36: Sale-price discount (back-order) | B36: B | C36: 5 | D36: €/unit short
A37: Purchase-price discount (B4) | B37: E | C37: 3 | D37: % on price v
A38: Lead time | B38: L | C38: 2 | D38: weeks

Sheet A1_Forecast
A1: PART A — Question 1 : Demand forecasting (simple exponential smoothing)
A2: Choice of smoothing constant α and forecast for months 25–36
A3: Method: aₜ = aₜ₋₁ + α·(xₜ − aₜ₋₁). Initial estimate a₁₁ = mean demand of the first 11 months. Accuracy is compared over months 13–24 with MSE, MAD, MAPE (error eₜ = xₜ − aₜ).
A5: Initial estimate a₁₁ = mean demand of months 1–11 : | F5: =AVERAGE(Data!B17:L17) -> 200.63636
B6: α → | C6: 0.1 | D6: 0.15 | E6: 0.2
A7: Forecast table aₜ for the three values of α
A8: t | B8: xₜ | C8: aₜ (α=0.10) | D8: aₜ (α=0.15) | E8: aₜ (α=0.20)
A9: 11 | B9: =Data!L17 -> 194 | C9: =F5 -> 200.63636 | D9: =F5 -> 200.63636 | E9: =F5 -> 200.63636
A10: 12 | B10: =Data!M17 -> 276 | C10: =C9+$C$6*(B10-C9) -> 208.17273 | D10: =D9+$D$6*(B10-D9) -> 211.94091 | E10: =E9+$E$6*(B10-E9) -> 215.70909
A11: 13 | B11: =Data!B19 -> 138 | C11: =C10+$C$6*(B11-C10) -> 201.15545 | D11: =D10+$D$6*(B11-D10) -> 200.84977 | E11: =E10+$E$6*(B11-E10) -> 200.16727
A12: 14 | B12: =Data!C19 -> 183 | C12: =C11+$C$6*(B12-C11) -> 199.33991 | D12: =D11+$D$6*(B12-D11) -> 198.17231 | E12: =E11+$E$6*(B12-E11) -> 196.73382
A13: 15 | B13: =Data!D19 -> 230 | C13: =C12+$C$6*(B13-C12) -> 202.40592 | D13: =D12+$D$6*(B13-D12) -> 202.94646 | E13: =E12+$E$6*(B13-E12) -> 203.38705
A14: 16 | B14: =Data!E19 -> 196 | C14: =C13+$C$6*(B14-C13) -> 201.76533 | D14: =D13+$D$6*(B14-D13) -> 201.90449 | E14: =E13+$E$6*(B14-E13) -> 201.90964
A15: 17 | B15: =Data!F19 -> 174 | C15: =C14+$C$6*(B15-C14) -> 198.98879 | D15: =D14+$D$6*(B15-D14) -> 197.71882 | E15: =E14+$E$6*(B15-E14) -> 196.32771
A16: 18 | B16: =Data!G19 -> 234 | C16: =C15+$C$6*(B16-C15) -> 202.48991 | D16: =D15+$D$6*(B16-D15) -> 203.161 | E16: =E15+$E$6*(B16-E15) -> 203.86217
A17: 19 | B17: =Data!H19 -> 244 | C17: =C16+$C$6*(B17-C16) -> 206.64092 | D17: =D16+$D$6*(B17-D16) -> 209.28685 | E17: =E16+$E$6*(B17-E16) -> 211.88974
A18: 20 | B18: =Data!I19 -> 245 | C18: =C17+$C$6*(B18-C17) -> 210.47683 | D18: =D17+$D$6*(B18-D17) -> 214.64382 | E18: =E17+$E$6*(B18-E17) -> 218.51179
A19: 21 | B19: =Data!J19 -> 176 | C19: =C18+$C$6*(B19-C18) -> 207.02915 | D19: =D18+$D$6*(B19-D18) -> 208.84725 | E19: =E18+$E$6*(B19-E18) -> 210.00943
A20: 22 | B20: =Data!K19 -> 140 | C20: =C19+$C$6*(B20-C19) -> 200.32623 | D20: =D19+$D$6*(B20-D19) -> 198.52016 | E20: =E19+$E$6*(B20-E19) -> 196.00755
A21: 23 | B21: =Data!L19 -> 215 | C21: =C20+$C$6*(B21-C20) -> 201.79361 | D21: =D20+$D$6*(B21-D20) -> 200.99214 | E21: =E20+$E$6*(B21-E20) -> 199.80604
A22: 24 | B22: =Data!M19 -> 149 | C22: =C21+$C$6*(B22-C21) -> 196.51425 | D22: =D21+$D$6*(B22-D21) -> 193.19332 | E22: =E21+$E$6*(B22-E21) -> 189.64483
A23: The shaded rows (months 13–24) are the accuracy-evaluation period.
A25: Accuracy comparison over months 13–24
A26: Error measure | B26: α = 0.10 | C26: α = 0.15 | D26: α = 0.20 | E26: Definition
A27: MSE | B27: =SUMPRODUCT((B11:B22-C11:C22)^2)/12 -> 1357.4355 | C27: =SUMPRODUCT((B11:B22-D11:D22)^2)/12 -> 1269.9998 | D27: =SUMPRODUCT((B11:B22-E11:E22)^2)/12 -> 1176.0346 | E27: mean squared error = Σ(xₜ−aₜ)²/12
A28: MAD | B28: =SUMPRODUCT(ABS(B11:B22-C11:C22))/12 -> 32.775993 | C28: =SUMPRODUCT(ABS(B11:B22-D11:D22))/12 -> 31.681321 | D28: =SUMPRODUCT(ABS(B11:B22-E11:E22))/12 -> 30.445289 | E28: mean absolute deviation = Σ|xₜ−aₜ|/12
A29: MAPE | B29: =SUMPRODUCT(ABS((B11:B22-C11:C22)/B11:B22))/12 -> 0.18801141 | C29: =SUMPRODUCT(ABS((B11:B22-D11:D22)/B11:B22))/12 -> 0.18222933 | D29: =SUMPRODUCT(ABS((B11:B22-E11:E22)/B11:B22))/12 -> 0.17541394 | E29: mean absolute percentage error = Σ|(xₜ−aₜ)/xₜ|/12
A30: Choice of α (minimum error) | B30: =INDEX({0.1,0.15,0.2},MATCH(MIN(B27:D27),B27:D27,0)) -> 0.2 | E30: All three measures are minimized at the same value → that α is chosen.
A32: Forecast for months 25–36
A33: Forecast = a₂₄ of the chosen α (constant for all months 25–36) : | F33: =INDEX(C22:E22,MATCH(B30,{0.1,0.15,0.2},0)) -> 189.64483
F34: ≈ units/month
A35: As there are no newer data, the forecast stays constant for all months 25–36. With new actual demand xₜ the forecast would be revised.

Sheet A2_A3_EOQ
A1: PART A — Questions 2 & 3 : EOQ, reorder point & discounts
A2: Constant demand at the forecast level (Question 1)
A4: Demand base (from the forecast)
A5: Monthly demand (rounded forecast) | D5: =ROUND(A1_Forecast!F33,0) -> 190 | E5: units/month | F5: forecast for months 25–36
A6: Annual demand D = 12 × monthly | D6: =12*D5 -> 2280 | E6: units/year
A8: Question 2 : Reorder point s & Economic Order Quantity (EOQ)
A9: L = 1 month. s = demand during lead time = monthly demand. EOQ = √(2·A·D / (v·r)), rounded to the nearest multiple of 10.
A10: Reorder point s = L · (monthly demand) | D10: =Data!C24*D5 -> 190 | E10: units | F10: when stock reaches here → new order
A11: EOQ (exact value) | D11: =SQRT(2*Data!C23*D6/(Data!C22*Data!C26)) -> 584.80766 | E11: units
A12: Q* = EOQ (multiple of 10) | D12: =MROUND(D11,10) -> 580 | E12: units
A14: Annual costs with Q = Q*
A15: Cost component | E15: €/year | F15: Explanation
A16: Ordering cost (D/Q)·A | D16: =D6/D12*Data!C23 -> 2948.2759 | F16: D/Q = order frequency
A17: Holding cost v·r·(Q/2) | D17: =Data!C22*Data!C26*D12/2 -> 2900 | F17: Q/2 = average inventory
A18: Total cost TC = ordering + holding cost | D18: =D16+D17 -> 5848.2759
A20: Question 3 : All-units quantity discounts
A21: Discount E% for Q ≥ 2000, or 2E% for Q ≥ 5000. We check whether accepting is worthwhile by comparing total cost (purchase + ordering + holding).
A22: Discount rate d₁ = E% | D22: =Data!C25/100 -> 0.01 | F22: for Q ≥ 2000
A23: Discount rate d₂ = 2E% | D23: =2*Data!C25/100 -> 0.02 | F23: for Q ≥ 5000
A24: EOQ with discount d₁ = √(2AD/(v(1−d₁)r)) | D24: =SQRT(2*Data!C23*D6/(Data!C22*(1-D22)*Data!C26)) -> 587.75381 | E24: units
A25: EOQ with discount d₂ | D25: =SQRT(2*Data!C23*D6/(Data!C22*(1-D23)*Data!C26)) -> 590.74495 | E25: units
A26: Both discounted EOQs are far below the thresholds (2000, 5000). So the discount can only be obtained by ordering exactly at the threshold Qb → we evaluate the cost at the thresholds.
A28: Total-cost comparison (includes purchase cost D·v)
A29: Scenario | B29: Quantity Q | C29: Discount | D29: Purchase cost D·v(1−d) | E29: Ordering (D/Q)A | F29: Holding v(1−d)r·Q/2 | G29: TOTAL TC
A30: Q* (no discount) | B30: =D12 -> 580 | C30: =0 -> 0 | D30: =D6*Data!C22*(1-C30) -> 228000 | E30: =D6/B30*Data!C23 -> 2948.2759 | F30: =Data!C22*(1-C30)*Data!C26*B30/2 -> 2900 | G30: =D30+E30+F30 -> 233848.28
A31: Qb₁ = 2000 (d₁) | B31: 2000 | C31: =D22 -> 0.01 | D31: =D6*Data!C22*(1-C31) -> 225720 | E31: =D6/B31*Data!C23 -> 855 | F31: =Data!C22*(1-C31)*Data!C26*B31/2 -> 9900 | G31: =D31+E31+F31 -> 236475
A32: Qb₂ = 5000 (d₂) | B32: 5000 | C32: =D23 -> 0.02 | D32: =D6*Data!C22*(1-C32) -> 223440 | E32: =D6/B32*Data!C23 -> 342 | F32: =Data!C22*(1-C32)*Data!C26*B32/2 -> 24500 | G32: =D32+E32+F32 -> 248282
A33: Best scenario → | G33: =MIN(G30:G32) -> 233848.28
A34: Conclusion: the lowest total cost occurs at Q* (no discount). The discounts do not offset the increase in holding cost from the very large quantities → they are NOT worthwhile.

Sheet B1_B2_Systems
A1: PART B — Questions 1 & 2 : Two (s, Q) systems & defense of the choice
A2: Stochastic weekly demand X ~ N(μ, σ²). L = 2 weeks.
A4: Common calculation base
A5: Demand during lead time: μ_L = L·μ, σ_L = √L·σ. Annual demand D = 52·μ. Order quantity Q from EOQ (common to both systems).
A6: μ_L = L · μ (mean demand during lead time) | D6: =Data!C38*Data!C31 -> 280 | E6: units
A7: σ_L = √L · σ (std. dev. during lead time) | D7: =SQRT(Data!C38)*Data!C32 -> 56.568542 | E7: units
A8: D = 52 · μ (annual demand) | D8: =52*Data!C31 -> 7280 | E8: units/year
A9: EOQ = √(2·A·D/(v·r)) | D9: =SQRT(2*Data!C35*D8/(Data!C33*Data!C34)) -> 426.61458 | E9: units
A10: Q = EOQ (rounded) | D10: =ROUND(D9,0) -> 427 | E10: units
A12: System 1 — Department's choice : target fill rate P₂ = 95%
A13: Given P₂ = 0.95. From P₂ = 1 − σ_L·G(k)/Q → G(k) = Q·(1−P₂)/σ_L. k is found by inverting the G(k) table (helper sheet _Tables).
A14: Target fill rate P₂ | D14: =0.95 -> 0.95
A15: Required G(k) = Q·(1−P₂)/σ_L | D15: =D10*(1-D14)/D7 -> 0.37741824
A16: Safety factor k (inversion of G(k)) | D16: =INDEX(_Tables!$A$4:$A$804,MATCH(D15,_Tables!$D$4:$D$804,-1)) -> 0.04 | F16: MATCH on descending G(k)
A17: Safety stock ss = k·σ_L | D17: =ROUND(D16*D7,0) -> 2 | E17: units
A18: Reorder point s = μ_L + ss | D18: =D6+D17 -> 282 | E18: units
A19: P₁ = Φ(k) (prob. of no stockout per cycle) | D19: =_xlfn.NORM.S.DIST(D16,TRUE()) -> 0.51595344
A20: System 1 : (s, Q) = (s₁, Q). Low ss → low inventory, but P₁ only ~52%.
A22: System 2 — GM's wish : stockout ≤ 1 in 20 orders → P₁ = 95%
A23: Given P₁ = 1 − 1/20 = 0.95 = Φ(k) → k = Φ⁻¹(0.95). From k we get ss, s and the corresponding fill rate P₂ = 1 − σ_L·G(k)/Q.
A24: Target P₁ = 1 − 1/20 | D24: =1-1/20 -> 0.95
A25: Safety factor k = Φ⁻¹(P₁) | D25: =_xlfn.NORM.S.INV(D24) -> 1.6448536
A26: Safety stock ss = k·σ_L | D26: =ROUND(D25*D7,0) -> 93 | E26: units
A27: Reorder point s = μ_L + ss | D27: =D6+D26 -> 373 | E27: units
A28: G(k) (direct formula φ(k)−k·(1−Φ(k))) | D28: =_xlfn.NORM.S.DIST(D25,FALSE())-D25*(1-_xlfn.NORM.S.DIST(D25,TRUE())) -> 0.020892959
A29: P₂ = 1 − σ_L·G(k)/Q (fill rate) | D29: =1-D7*D28/D10 -> 0.99723212
A30: System 2 : (s, Q) = (s₂, Q). Very high ss → P₂ ≈ 99.7%, but large safety stock.
A32: Question 2 — Cost comparison & defense of the choice
A33: Average inventory = ss + Q/2. Ordering = (D/Q)·A. Holding = v·r·(ss + Q/2). Shortage = B·(1−P₁)·(D/Q) [B = discount per unit short · expected stockouts/year].
A34: Quantity | E34: System 1 (Dept) | G34: System 2 (GM)
A35: Average inventory = ss + Q/2 | E35: =D17+D10/2 -> 215.5 | G35: =D26+D10/2 -> 306.5
A36: Ordering cost (D/Q)·A | E36: =D8/D10*Data!C35 -> 1704.918 | G36: =D8/D10*Data!C35 -> 1704.918
A37: Holding cost v·r·(ss+Q/2) | E37: =Data!C33*Data!C34*(D17+D10/2) -> 1724 | G37: =Data!C33*Data!C34*(D26+D10/2) -> 2452
A38: Shortage cost B·(1−P₁)·(D/Q) | E38: =Data!C36*(1-D19)*D8/D10 -> 41.262986 | G38: =Data!C36*(1-D24)*D8/D10 -> 4.2622951
A39: Total annual cost TC | E39: =E36+E37+E38 -> 3470.181 | G39: =G36+G37+G38 -> 4161.1803
A41: Argument: System 1 (P₂=95%) holds far less safety stock than System 2 (P₁=95%) and has a LOWER total cost. The difference over 18 months (1.5 years):
A42: Department saving over 18 months = (TC₂ − TC₁)·1.5 | D42: =(G39-E39)*1.5 -> 1036.499 | E42: € | F42: positive → the Department made the right choice
A43: Conclusion: the Department's choice (95% fill rate) did NOT cost the company — on the contrary it saved money, maintaining a reasonable service level with much less inventory.

Sheet B3_Improved
A1: PART B — Question 3 : Improved (s, Q) system with shortage cost
A2: Joint determination of s and Q taking the shortage cost B into account.
A4: Improved system — System 3
A5: With shortage cost B €/unit, the optimal reorder point satisfies 1 − Φ(k) = Q·v·r / (B·D) (the per-cycle stockout probability depends on Q → s–Q interdependence). Q stays = EOQ from the previous sheet.
A6: Base (from sheet B1_B2): μ_L, σ_L, D and Q = EOQ.
A7: Per-cycle stockout probability 1−Φ(k) = Q·v·r/(B·D) | D7: =B1_B2_Systems!D10*Data!C33*Data!C34/(Data!C36*B1_B2_Systems!D8) -> 0.093846154 | F7: improved condition (correction)
A8: Safety factor k = Φ⁻¹(1 − (Q·v·r/(B·D))) | D8: =_xlfn.NORM.S.INV(1-D7) -> 1.3174366
A9: Safety stock ss = k·σ_L | D9: =ROUND(D8*B1_B2_Systems!D7,0) -> 75 | E9: units
A10: Reorder point s = μ_L + ss | D10: =B1_B2_Systems!D6+D9 -> 355 | E10: units
A11: G(k) = φ(k) − k·(1−Φ(k)) | D11: =_xlfn.NORM.S.DIST(D8,FALSE())-D8*(1-_xlfn.NORM.S.DIST(D8,TRUE())) -> 0.043865942
A12: P₂ = 1 − σ_L·G(k)/Q (fill rate) | D12: =1-B1_B2_Systems!D7*D11/B1_B2_Systems!D10 -> 0.99418868
A13: Improved system 3 : (s, Q) = (s₃, Q), with fill rate P₂ ≈ 99%.
A15: Comparison of the three (s, Q) systems
A16: Shortage cost: B·(1−Φ(k))·(D/Q) (uniform convention: cost per cycle with a stockout). Systems 1 & 2 are drawn from sheet B1_B2.
A17: Quantity | C17: System 1 (Dept, P₂=95%) | E17: System 2 (GM, P₁=95%) | G17: System 3 (Improved)
A18: Reorder point s | C18: =B1_B2_Systems!D18 -> 282 | E18: =B1_B2_Systems!D27 -> 373 | G18: =D10 -> 355
A19: Safety stock ss | C19: =B1_B2_Systems!D17 -> 2 | E19: =B1_B2_Systems!D26 -> 93 | G19: =D9 -> 75
A20: Average inventory ss+Q/2 | C20: =B1_B2_Systems!E35 -> 215.5 | E20: =B1_B2_Systems!G35 -> 306.5 | G20: =D9+B1_B2_Systems!D10/2 -> 288.5
A21: Fill rate P₂ | C21: =B1_B2_Systems!D14 -> 0.95 | E21: =B1_B2_Systems!D29 -> 0.99723212 | G21: =D12 -> 0.99418868
A22: Ordering cost | C22: =B1_B2_Systems!E36 -> 1704.918 | E22: =B1_B2_Systems!G36 -> 1704.918 | G22: =B1_B2_Systems!D8/B1_B2_Systems!D10*Data!C35 -> 1704.918
A23: Holding cost | C23: =B1_B2_Systems!E37 -> 1724 | E23: =B1_B2_Systems!G37 -> 2452 | G23: =Data!C33*Data!C34*(D9+B1_B2_Systems!D10/2) -> 2308
A24: Shortage cost | C24: =B1_B2_Systems!E38 -> 41.262986 | E24: =B1_B2_Systems!G38 -> 4.2622951 | G24: =Data!C36*D7*B1_B2_Systems!D8/B1_B2_Systems!D10 -> 8
A25: TOTAL COST TC | C25: =B1_B2_Systems!E39 -> 3470.181 | E25: =B1_B2_Systems!G39 -> 4161.1803 | G25: =G22+G23+G24 -> 4020.918
A27: Conclusion: System 1 (Department's choice, P₂=95%) remains the CHEAPEST in total cost. The improved System 3 substantially improves on System 2 (much lower inventory/cost) and achieves a high fill rate (~99%), but does not beat System 1 on cost.

Sheet B4_Periodic
A1: PART B — Question 4 : Periodic (R, S) system & final recommendation
A2: Order 1×/month (R=4 wks) or 2×/month (R=2 wks). Protection interval R+L.
A4: Common base — protection interval R + L (L = 2 wks)
A5: Quantity | D5: R₁ = 4 wks (1×/month) | F5: R₂ = 2 wks (2×/month)
A6: Review period R (weeks) | D6: =4 -> 4 | F6: =2 -> 2
A7: Protection interval R + L | D7: =D6+Data!C38 -> 6 | F7: =F6+Data!C38 -> 4
A8: μ(R+L) = (R+L)·μ | D8: =D7*Data!C31 -> 840 | F8: =F7*Data!C31 -> 560
A9: σ(R+L) = √(R+L)·σ | D9: =SQRT(D7)*Data!C32 -> 97.97959 | F9: =SQRT(F7)*Data!C32 -> 80
A10: Demand per cycle = μ·R | D10: =Data!C31*D6 -> 560 | F10: =Data!C31*F6 -> 280
A12: 4a — Target: stockout ≤ 1 in 20 orders → P₁ = 95%
A13: S = μ(R+L) + k·σ(R+L), with k = Φ⁻¹(0.95) = 1.645. Mean time between stockouts TBS = R / (1 − P₁).
A14: Quantity | D14: R₁ = 4 wks (1×/month) | F14: R₂ = 2 wks (2×/month)
A15: k = Φ⁻¹(P₁) , P₁ = 1−1/20 | D15: =_xlfn.NORM.S.INV(1-1/20) -> 1.6448536 | F15: =_xlfn.NORM.S.INV(1-1/20) -> 1.6448536
A16: Order-up-to level S = μ(R+L)+k·σ(R+L) | D16: =ROUND(D8+D15*D9,0) -> 1001 | F16: =ROUND(F8+F15*F9,0) -> 692
A17: TBS = R/(1−P₁) (weeks) | D17: =D6/(1-_xlfn.NORM.S.DIST(D15,TRUE())) -> 80 | F17: =F6/(1-_xlfn.NORM.S.DIST(F15,TRUE())) -> 40
A18: Systems: (R,S) = (4, S₁) and (R,S) = (2, S₂). High service level, higher inventory cost.
A20: 4b — Target: minimize total cost (with shortage cost B)
A21: Critical ratio CR = B / (B + v·r·R) [R in years] → k = Φ⁻¹(CR). (Correction: the v·r·R term must not be omitted.) S = μ(R+L) + k·σ(R+L).
A22: Quantity | D22: R₁ = 4 wks (1×/month) | F22: R₂ = 2 wks (2×/month)
A23: R in years = R/52 | D23: =D6/52 -> 0.076923077 | F23: =F6/52 -> 0.038461538
A24: Critical ratio CR = B/(B+v·r·R) | D24: =Data!C36/(Data!C36+Data!C33*Data!C34*D23) -> 0.89041096 | F24: =Data!C36/(Data!C36+Data!C33*Data!C34*F23) -> 0.94202899
A25: k = Φ⁻¹(CR) | D25: =_xlfn.NORM.S.INV(D24) -> 1.2287166 | F25: =_xlfn.NORM.S.INV(F24) -> 1.5720367
A26: Order-up-to level S = μ(R+L)+k·σ(R+L) | D26: =ROUND(D8+D25*D9,0) -> 960 | F26: =ROUND(F8+F25*F9,0) -> 686
A27: G(k) = φ(k)−k·(1−Φ(k)) | D27: =_xlfn.NORM.S.DIST(D25,FALSE())-D25*(1-_xlfn.NORM.S.DIST(D25,TRUE())) -> 0.052877192 | F27: =_xlfn.NORM.S.DIST(F25,FALSE())-F25*(1-_xlfn.NORM.S.DIST(F25,TRUE())) -> 0.024818352
A28: Fill rate P₂ = 1 − σ(R+L)·G(k)/(μ·R) | D28: =1-D9*D27/D10 -> 0.99074842 | F28: =1-F9*F27/F10 -> 0.99290904
A29: TBS = R/(1−Φ(k)) (weeks) | D29: =D6/(1-_xlfn.NORM.S.DIST(D25,TRUE())) -> 36.5 | F29: =F6/(1-_xlfn.NORM.S.DIST(F25,TRUE())) -> 34.5
A31: 4c — Final comparison & recommendation (E% price discount ONLY for the periodic (R,S))
A32: Discounted purchase price v' = v·(1−E%) | F32: =Data!C33*(1-Data!C37/100) -> 77.6 | G32: €/unit
A33: Cost per system = Purchase (D·price) + Ordering (A/R_yr or (D/Q)A) + Holding + Shortage. The 3% discount applies only if we accept fixed periods (supplier proposal).
A34: System | C34: S or (s,Q) | D34: Fill rate P₂ | E34: Purchase cost | F34: Operating (order+hold+short) | G34: TOTAL TC
A35: (R,S) R₁=4, P₁=95% | C35: =D16 -> 1001 | D35: =1-D9*(_xlfn.NORM.S.DIST(D15,FALSE())-D15*(1-_xlfn.NORM.S.DIST(D15,TRUE())))/D10 -> 0.99634449 | E35: =B1_B2_Systems!D8*F32 -> 564928 | F35: =Data!C35/D23+F32*Data!C34*(D15*D9+D10/2)+Data!C36*(1-_xlfn.NORM.S.DIST(D15,TRUE()))/D23 -> 4726.6678 | G35: =E35+F35 -> 569654.67
A36: (R,S) R₂=2, P₁=95% | C36: =F16 -> 692 | D36: =1-F9*(_xlfn.NORM.S.DIST(F15,FALSE())-F15*(1-_xlfn.NORM.S.DIST(F15,TRUE())))/F10 -> 0.99403058 | E36: =B1_B2_Systems!D8*F32 -> 564928 | F36: =Data!C35/F23+F32*Data!C34*(F15*F9+F10/2)+Data!C36*(1-_xlfn.NORM.S.DIST(F15,TRUE()))/F23 -> 4714.0251 | G36: =E36+F36 -> 569642.03
A37: (R,S) R₁=4, min cost | C37: =D26 -> 960 | D37: =D28 -> 0.99074842 | E37: =B1_B2_Systems!D8*F32 -> 564928 | F37: =Data!C35/D23+F32*Data!C34*(D25*D9+D10/2)+Data!C36*(1-_xlfn.NORM.S.DIST(D25,TRUE()))/D23 -> 4414.1431 | G37: =E37+F37 -> 569342.14
A38: (R,S) R₂=2, min cost | C38: =F26 -> 686 | D38: =F28 -> 0.99290904 | E38: =B1_B2_Systems!D8*F32 -> 564928 | F38: =Data!C35/F23+F32*Data!C34*(F25*F9+F10/2)+Data!C36*(1-_xlfn.NORM.S.DIST(F25,TRUE()))/F23 -> 4669.8566 | G38: =E38+F38 -> 569597.86
A39: (s,Q) improved (full price) | C39: =B3_Improved!D10 -> 355 | D39: =B3_Improved!D12 -> 0.99418868 | E39: =B1_B2_Systems!D8*Data!C33 -> 582400 | F39: =B3_Improved!G25 -> 4020.918 | G39: =E39+F39 -> 586420.92
A40: Minimum total cost → | G40: =MIN(G35:G39) -> 569342.14
A41: RECOMMENDATION: All periodic (R,S) systems with the 3% discount are clearly cheaper than (s,Q) at full price — the purchase-price discount (~€17,000/year) outweighs the differences in the other costs. Therefore accepting the supplier's proposal IS worthwhile.
A42: Between the two periods, ordering once/month (R₁=4 wks) gives the lowest total cost (lower ordering cost). Final recommendation to the GM: accept a fixed period, ordering once a month.

Sheet _Tables
A1: Standard normal distribution & loss function G(k) table
A2: Helper table. G(k)=φ(k)−k·[1−Φ(k)]. Used to invert G(k)→k (find k from a target fill rate).
A3: k | B3: φ(k) | C3: Φ(k) | D3: G(k)
A4: 0 | B4: =_xlfn.NORM.S.DIST(A4,FALSE()) -> 0.39894228 | C4: =_xlfn.NORM.S.DIST(A4,TRUE()) -> 0.5 | D4: =B4-A4*(1-C4) -> 0.39894228
A5: 0.005 | B5: =_xlfn.NORM.S.DIST(A5,FALSE()) -> 0.39893729 | C5: =_xlfn.NORM.S.DIST(A5,TRUE()) -> 0.5019947 | D5: =B5-A5*(1-C5) -> 0.39644727
A6: 0.01 | B6: =_xlfn.NORM.S.DIST(A6,FALSE()) -> 0.39892233 | C6: =_xlfn.NORM.S.DIST(A6,TRUE()) -> 0.50398936 | D6: =B6-A6*(1-C6) -> 0.39396223
A7: 0.015 | B7: =_xlfn.NORM.S.DIST(A7,FALSE()) -> 0.3988974 | C7: =_xlfn.NORM.S.DIST(A7,TRUE()) -> 0.50598391 | D7: =B7-A7*(1-C7) -> 0.39148716
A8: 0.02 | B8: =_xlfn.NORM.S.DIST(A8,FALSE()) -> 0.3988625 | C8: =_xlfn.NORM.S.DIST(A8,TRUE()) -> 0.50797831 | D8: =B8-A8*(1-C8) -> 0.38902207
A9: 0.025 | B9: =_xlfn.NORM.S.DIST(A9,FALSE()) -> 0.39881763 | C9: =_xlfn.NORM.S.DIST(A9,TRUE()) -> 0.50997252 | D9: =B9-A9*(1-C9) -> 0.38656694
A10: 0.03 | B10: =_xlfn.NORM.S.DIST(A10,FALSE()) -> 0.3987628 | C10: =_xlfn.NORM.S.DIST(A10,TRUE()) -> 0.51196647 | D10: =B10-A10*(1-C10) -> 0.38412179
A11: 0.035 | B11: =_xlfn.NORM.S.DIST(A11,FALSE()) -> 0.398698 | C11: =_xlfn.NORM.S.DIST(A11,TRUE()) -> 0.51396013 | D11: =B11-A11*(1-C11) -> 0.38168661
A12: 0.04 | B12: =_xlfn.NORM.S.DIST(A12,FALSE()) -> 0.39862325 | C12: =_xlfn.NORM.S.DIST(A12,TRUE()) -> 0.51595344 | D12: =B12-A12*(1-C12) -> 0.37926139
A13: 0.045 | B13: =_xlfn.NORM.S.DIST(A13,FALSE()) -> 0.39853856 | C13: =_xlfn.NORM.S.DIST(A13,TRUE()) -> 0.51794635 | D13: =B13-A13*(1-C13) -> 0.37684614
A14: 0.05 | B14: =_xlfn.NORM.S.DIST(A14,FALSE()) -> 0.39844391 | C14: =_xlfn.NORM.S.DIST(A14,TRUE()) -> 0.51993881 | D14: =B14-A14*(1-C14) -> 0.37444085
A15: 0.055 | B15: =_xlfn.NORM.S.DIST(A15,FALSE()) -> 0.39833934 | C15: =_xlfn.NORM.S.DIST(A15,TRUE()) -> 0.52193077 | D15: =B15-A15*(1-C15) -> 0.37204553
... A804: 4 | B804: =_xlfn.NORM.S.DIST(A804,FALSE()) -> 0.00013383023 | C804: =_xlfn.NORM.S.DIST(A804,TRUE()) -> 0.99996833 | D804: =B804-A804*(1-C804) -> 7.1452584e-06
